rioxarray/__init__.py
rioxarray/_io.py
rioxarray/_options.py
rioxarray/_show_versions.py
rioxarray/_spatial_utils.py
rioxarray/crs.py
rioxarray/exceptions.py
rioxarray/merge.py
rioxarray/py.typed
rioxarray/raster_array.py
rioxarray/raster_dataset.py
rioxarray/raster_writer.py
rioxarray/rioxarray.py
rioxarray/xarray_plugin.py
rioxarray-0.21.0.dist-info/licenses/AUTHORS.rst
rioxarray-0.21.0.dist-info/licenses/LICENSE
rioxarray-0.21.0.dist-info/licenses/LICENSE_datacube
rioxarray-0.21.0.dist-info/licenses/LICENSE_xarray
rioxarray-0.21.0.dist-info/METADATA
rioxarray-0.21.0.dist-info/WHEEL
rioxarray-0.21.0.dist-info/entry_points.txt
rioxarray-0.21.0.dist-info/top_level.txt
rioxarray-0.21.0.dist-info/RECORD
