Metadata-Version: 2.4
Name: rioxarray
Version: 0.21.0
Summary: geospatial xarray extension powered by rasterio
Maintainer: rioxarray Contributors
License: Apache
Project-URL: homepage, https://corteva.github.io/rioxarray/
Project-URL: documentation, https://corteva.github.io/rioxarray/
Project-URL: repository, https://github.com/corteva/rioxarray
Project-URL: changelog, https://corteva.github.io/rioxarray/stable/history.html
Keywords: rioxarray,xarray,rasterio
Classifier: Development Status :: 4 - Beta
Classifier: Intended Audience :: Developers
Classifier: Natural Language :: English
Classifier: License :: OSI Approved :: Apache Software License
Classifier: Operating System :: OS Independent
Classifier: Topic :: Scientific/Engineering :: GIS
Classifier: Programming Language :: Python
Classifier: Programming Language :: Python :: 3.12
Classifier: Programming Language :: Python :: 3.13
Classifier: Programming Language :: Python :: 3.14
Classifier: Programming Language :: Python :: 3
Classifier: Topic :: Software Development :: Libraries :: Python Modules
Classifier: Typing :: Typed
Requires-Python: >=3.12
License-File: LICENSE
License-File: LICENSE_datacube
License-File: LICENSE_xarray
License-File: AUTHORS.rst
Requires-Dist: packaging
Requires-Dist: rasterio>=1.4.3
Requires-Dist: xarray<2025.12,>=2024.7.0
Requires-Dist: pyproj>=3.3
Requires-Dist: numpy>=2
Provides-Extra: interp
Requires-Dist: scipy; extra == "interp"
Provides-Extra: all
Requires-Dist: scipy; extra == "all"
Dynamic: license-file
